G31_KID_design/Array.py
G31_KID_design/HilbertIShape.py
G31_KID_design/HilbertLShape.py
G31_KID_design/Patterns.py
G31_KID_design/__init__.py
G31_KID_design-1.0.3.dist-info/METADATA
G31_KID_design-1.0.3.dist-info/WHEEL
G31_KID_design-1.0.3.dist-info/top_level.txt
G31_KID_design-1.0.3.dist-info/RECORD
