Metadata-Version: 2.1
Name: G31_KID_design
Version: 1.0.3
Summary: An AutoCAD library for KID design
Author-email: Federico Cacciotti <federico.cacciotti@roma1.infn.it>
Project-URL: Homepage, https://github.com/federico-cacciotti/G31_KID_design
Classifier: Programming Language :: Python :: 3
Classifier: License :: OSI Approved :: MIT License
Classifier: Operating System :: OS Independent
Requires-Python: >=3.7
